ptuevents/__init__.py
ptuevents/filtersets.py
ptuevents/forms.py
ptuevents/graphql.py
ptuevents/models.py
ptuevents/navigation.py
ptuevents/tables.py
ptuevents/template_content.py
ptuevents/urls.py
ptuevents/views.py
ptuevents/api/__init__.py
ptuevents/api/serializers.py
ptuevents/api/urls.py
ptuevents/api/views.py
ptuevents/migrations/0001_initial.py
ptuevents/migrations/__init__.py
ptuevents/templates/ptuevents/appsystem_assignment_edit.html
ptuevents/templates/ptuevents/appsystem_panel.html
ptuevents/templates/ptuevents/ptappsystem.html
ptuevents/templates/ptuevents/ptuevent.html
ptuevents/templates/ptuevents/ptuevent_assignment_edit.html
ptuevents/templates/ptuevents/ptuevent_panel.html
ptuevents/templates/ptuevents/ptueventrelation.html
ptuevents/templates/ptuevents/ptusers.html
ptuevents/templates/ptuevents/ptusers_add.html
ptuevents/templates/ptuevents/ptworkstations.html
ptuevents/templates/ptuevents/ptworkstations_assignment_edit.html
ptuevents/templates/ptuevents/ptworkstations_panel.html
netbox_unacceptable_events_users_computers-0.1.3.134.dist-info/LICENSE
netbox_unacceptable_events_users_computers-0.1.3.134.dist-info/METADATA
netbox_unacceptable_events_users_computers-0.1.3.134.dist-info/WHEEL
netbox_unacceptable_events_users_computers-0.1.3.134.dist-info/top_level.txt
netbox_unacceptable_events_users_computers-0.1.3.134.dist-info/RECORD
